llama_index/graph_stores/agensgraph/__init__.py
llama_index/graph_stores/agensgraph/agensgraph_property_graph.py
llama_index/graph_stores/agensgraph/base.py
llama_index/graph_stores/agensgraph/utils.py
llama_index_graph_stores_agensgraph-0.1.0.dist-info/LICENSE
llama_index_graph_stores_agensgraph-0.1.0.dist-info/METADATA
llama_index_graph_stores_agensgraph-0.1.0.dist-info/WHEEL
llama_index_graph_stores_agensgraph-0.1.0.dist-info/RECORD
