Metadata-Version: 2.3
Name: llama-index-graph-stores-agensgraph
Version: 0.1.0
Summary: llama-index graph stores agensgraph integration
Keywords: llama-index,agensgraph,graph store,integration
Author: Muhammad Taha Naveed
Author-email: skaisw@skaiworldwide.com
Requires-Python: >=3.9,<4.0
Classifier: Programming Language :: Python :: 3
Classifier: Programming Language :: Python :: 3.9
Classifier: Programming Language :: Python :: 3.10
Classifier: Programming Language :: Python :: 3.11
Classifier: Programming Language :: Python :: 3.12
Classifier: Programming Language :: Python :: 3.13
Requires-Dist: llama-index-core (>=0.12.0,<0.13.0)
Requires-Dist: psycopg2 (>=2.9.10,<3.0.0)
Project-URL: Homepage, https://github.com/skaiworldwide-oss/agensgraph-ai/tree/main/llama-index
Project-URL: Repository, https://github.com/skaiworldwide-oss/agensgraph-ai/tree/main/llama-index
